{
  "6007": {
    "DungeonId": 6007,
    "DungeonGroup": 3,
    "StarLevel": 1,
    "LabelPic": "ui/textures/herodungeon/hero_dungeon_tab_gebulin_1",
    "Background": "ui/textures/dungeon_textures/dungeon_gebulin_1",
    "MasterModePic": "",
    "ModelId": 1,
    "EffectId": "1",
    "ExtraTarget": [],
    "BaseRatio": 100,
    "Affix": [],
    "SwitchAffix": [
      [
        115
      ],
      [
        104
      ],
      [
        106
      ],
      [
        102
      ],
      [
        108
      ],
      [
        104
      ],
      [
        106
      ],
      [
        102
      ],
      [
        108
      ],
      [
        104
      ],
      [
        106
      ],
      [
        102
      ],
      [
        108
      ]
    ],
    "SelectAffix": [],
    "ScoreRank": [],
    "LimitTime": 0,
    "ScoreAward": [],
    "KeyReward": []
  },
  "6008": {
    "DungeonId": 6008,
    "DungeonGroup": 3,
    "StarLevel": 2,
    "LabelPic": "ui/textures/herodungeon/hero_dungeon_tab_gebulin_2",
    "Background": "ui/textures/dungeon_textures/dungeon_gebulin_2",
    "MasterModePic": "",
    "ModelId": 1,
    "EffectId": "1",
    "ExtraTarget": [],
    "BaseRatio": 100,
    "Affix": [],
    "SwitchAffix": [
      [
        115
      ],
      [
        104
      ],
      [
        106
      ],
      [
        102
      ],
      [
        108
      ],
      [
        104
      ],
      [
        106
      ],
      [
        102
      ],
      [
        108
      ],
      [
        104
      ],
      [
        106
      ],
      [
        102
      ],
      [
        108
      ]
    ],
    "SelectAffix": [],
    "ScoreRank": [],
    "LimitTime": 0,
    "ScoreAward": [],
    "KeyReward": []
  },
  "6009": {
    "DungeonId": 6009,
    "DungeonGroup": 3,
    "StarLevel": 3,
    "LabelPic": "ui/textures/herodungeon/hero_dungeon_tab_gebulin_3",
    "Background": "ui/textures/dungeon_textures/dungeon_gebulin_3",
    "MasterModePic": "ui/textures/hero_dungeon_master/master_gebulin_title_01",
    "ModelId": 1,
    "EffectId": "1",
    "ExtraTarget": [],
    "BaseRatio": 100,
    "Affix": [],
    "SwitchAffix": [],
    "SelectAffix": [],
    "ScoreRank": [],
    "LimitTime": 0,
    "ScoreAward": [],
    "KeyReward": []
  },
  "1031": {
    "DungeonId": 1031,
    "DungeonGroup": 2,
    "StarLevel": 1,
    "LabelPic": "ui/textures/herodungeon/hero_dungeon_tab_01",
    "Background": "ui/textures/dungeon_textures/dungeon_dina_1",
    "MasterModePic": "",
    "ModelId": 1,
    "EffectId": "1",
    "ExtraTarget": [],
    "BaseRatio": 100,
    "Affix": [],
    "SwitchAffix": [
      [
        115
      ],
      [
        104
      ],
      [
        106
      ],
      [
        102
      ],
      [
        108
      ],
      [
        104
      ],
      [
        106
      ],
      [
        102
      ],
      [
        108
      ],
      [
        104
      ],
      [
        106
      ],
      [
        102
      ],
      [
        108
      ]
    ],
    "SelectAffix": [],
    "ScoreRank": [],
    "LimitTime": 0,
    "ScoreAward": [],
    "KeyReward": []
  },
  "1032": {
    "DungeonId": 1032,
    "DungeonGroup": 2,
    "StarLevel": 2,
    "LabelPic": "ui/textures/herodungeon/hero_dungeon_tab_03",
    "Background": "ui/textures/dungeon_textures/dungeon_dina_3",
    "MasterModePic": "",
    "ModelId": 1,
    "EffectId": "1",
    "ExtraTarget": [],
    "BaseRatio": 100,
    "Affix": [],
    "SwitchAffix": [
      [
        115
      ],
      [
        104
      ],
      [
        106
      ],
      [
        102
      ],
      [
        108
      ],
      [
        104
      ],
      [
        106
      ],
      [
        102
      ],
      [
        108
      ],
      [
        104
      ],
      [
        106
      ],
      [
        102
      ],
      [
        108
      ]
    ],
    "SelectAffix": [],
    "ScoreRank": [],
    "LimitTime": 0,
    "ScoreAward": [],
    "KeyReward": []
  },
  "1033": {
    "DungeonId": 1033,
    "DungeonGroup": 2,
    "StarLevel": 3,
    "LabelPic": "ui/textures/herodungeon/hero_dungeon_tab_02",
    "Background": "ui/textures/dungeon_textures/dungeon_dina_2",
    "MasterModePic": "ui/textures/hero_dungeon_master/master_dina_title_01",
    "ModelId": 1,
    "EffectId": "1",
    "ExtraTarget": [],
    "BaseRatio": 100,
    "Affix": [],
    "SwitchAffix": [],
    "SelectAffix": [],
    "ScoreRank": [],
    "LimitTime": 0,
    "ScoreAward": [],
    "KeyReward": []
  },
  "1121": {
    "DungeonId": 1121,
    "DungeonGroup": 1,
    "StarLevel": 1,
    "LabelPic": "ui/textures/herodungeon/hero_dungeon_tab_07",
    "Background": "ui/textures/dungeon_textures/dungeon_juta_1",
    "MasterModePic": "",
    "ModelId": 1,
    "EffectId": "1",
    "ExtraTarget": [],
    "BaseRatio": 100,
    "Affix": [],
    "SwitchAffix": [
      [
        115
      ],
      [
        104
      ],
      [
        106
      ],
      [
        102
      ],
      [
        108
      ],
      [
        104
      ],
      [
        106
      ],
      [
        102
      ],
      [
        108
      ],
      [
        104
      ],
      [
        106
      ],
      [
        102
      ],
      [
        108
      ]
    ],
    "SelectAffix": [],
    "ScoreRank": [],
    "LimitTime": 0,
    "ScoreAward": [],
    "KeyReward": []
  },
  "1122": {
    "DungeonId": 1122,
    "DungeonGroup": 1,
    "StarLevel": 2,
    "LabelPic": "ui/textures/herodungeon/hero_dungeon_tab_09",
    "Background": "ui/textures/dungeon_textures/dungeon_juta_3",
    "MasterModePic": "",
    "ModelId": 1,
    "EffectId": "1",
    "ExtraTarget": [],
    "BaseRatio": 100,
    "Affix": [],
    "SwitchAffix": [
      [
        115
      ],
      [
        104
      ],
      [
        106
      ],
      [
        102
      ],
      [
        108
      ],
      [
        104
      ],
      [
        106
      ],
      [
        102
      ],
      [
        108
      ],
      [
        104
      ],
      [
        106
      ],
      [
        102
      ],
      [
        108
      ]
    ],
    "SelectAffix": [],
    "ScoreRank": [],
    "LimitTime": 0,
    "ScoreAward": [],
    "KeyReward": []
  },
  "1123": {
    "DungeonId": 1123,
    "DungeonGroup": 1,
    "StarLevel": 3,
    "LabelPic": "ui/textures/herodungeon/hero_dungeon_tab_08",
    "Background": "ui/textures/dungeon_textures/dungeon_juta_2",
    "MasterModePic": "ui/textures/hero_dungeon_master/master_juta_title_01",
    "ModelId": 1,
    "EffectId": "1",
    "ExtraTarget": [],
    "BaseRatio": 100,
    "Affix": [],
    "SwitchAffix": [],
    "SelectAffix": [],
    "ScoreRank": [],
    "LimitTime": 0,
    "ScoreAward": [],
    "KeyReward": []
  },
  "6021": {
    "DungeonId": 6021,
    "DungeonGroup": 4,
    "StarLevel": 1,
    "LabelPic": "ui/textures/herodungeon/hero_dungeon_tab_10",
    "Background": "ui/textures/dungeon_textures/dungeon_kaniman_1",
    "MasterModePic": "",
    "ModelId": 1,
    "EffectId": "1",
    "ExtraTarget": [],
    "BaseRatio": 100,
    "Affix": [],
    "SwitchAffix": [
      [
        115
      ],
      [
        104
      ],
      [
        106
      ],
      [
        102
      ],
      [
        108
      ],
      [
        104
      ],
      [
        106
      ],
      [
        102
      ],
      [
        108
      ],
      [
        104
      ],
      [
        106
      ],
      [
        102
      ],
      [
        108
      ]
    ],
    "SelectAffix": [],
    "ScoreRank": [],
    "LimitTime": 0,
    "ScoreAward": [],
    "KeyReward": []
  },
  "6022": {
    "DungeonId": 6022,
    "DungeonGroup": 4,
    "StarLevel": 2,
    "LabelPic": "ui/textures/herodungeon/hero_dungeon_tab_11",
    "Background": "ui/textures/dungeon_textures/dungeon_kaniman_2",
    "MasterModePic": "",
    "ModelId": 1,
    "EffectId": "1",
    "ExtraTarget": [],
    "BaseRatio": 100,
    "Affix": [],
    "SwitchAffix": [
      [
        115
      ],
      [
        104
      ],
      [
        106
      ],
      [
        102
      ],
      [
        108
      ],
      [
        104
      ],
      [
        106
      ],
      [
        102
      ],
      [
        108
      ],
      [
        104
      ],
      [
        106
      ],
      [
        102
      ],
      [
        108
      ]
    ],
    "SelectAffix": [],
    "ScoreRank": [],
    "LimitTime": 0,
    "ScoreAward": [],
    "KeyReward": []
  },
  "6023": {
    "DungeonId": 6023,
    "DungeonGroup": 4,
    "StarLevel": 3,
    "LabelPic": "ui/textures/herodungeon/hero_dungeon_tab_12",
    "Background": "ui/textures/dungeon_textures/dungeon_kaniman_3",
    "MasterModePic": "ui/textures/hero_dungeon_master/master_kaniman_title_01",
    "ModelId": 1,
    "EffectId": "1",
    "ExtraTarget": [],
    "BaseRatio": 100,
    "Affix": [],
    "SwitchAffix": [],
    "SelectAffix": [],
    "ScoreRank": [],
    "LimitTime": 0,
    "ScoreAward": [],
    "KeyReward": []
  },
  "1221": {
    "DungeonId": 1221,
    "DungeonGroup": 5,
    "StarLevel": 1,
    "LabelPic": "ui/textures/herodungeon/hero_dungeon_tab_04",
    "Background": "ui/textures/dungeon_textures/dungeon_julong_1",
    "MasterModePic": "",
    "ModelId": 1,
    "EffectId": "1",
    "ExtraTarget": [],
    "BaseRatio": 100,
    "Affix": [],
    "SwitchAffix": [
      [
        115
      ],
      [
        104
      ],
      [
        106
      ],
      [
        102
      ],
      [
        108
      ],
      [
        104
      ],
      [
        106
      ],
      [
        102
      ],
      [
        108
      ],
      [
        104
      ],
      [
        106
      ],
      [
        102
      ],
      [
        108
      ]
    ],
    "SelectAffix": [],
    "ScoreRank": [],
    "LimitTime": 0,
    "ScoreAward": [],
    "KeyReward": []
  },
  "1222": {
    "DungeonId": 1222,
    "DungeonGroup": 5,
    "StarLevel": 2,
    "LabelPic": "ui/textures/herodungeon/hero_dungeon_tab_05",
    "Background": "ui/textures/dungeon_textures/dungeon_julong_2",
    "MasterModePic": "",
    "ModelId": 1,
    "EffectId": "1",
    "ExtraTarget": [],
    "BaseRatio": 100,
    "Affix": [],
    "SwitchAffix": [
      [
        115
      ],
      [
        104
      ],
      [
        106
      ],
      [
        102
      ],
      [
        108
      ],
      [
        104
      ],
      [
        106
      ],
      [
        102
      ],
      [
        108
      ],
      [
        104
      ],
      [
        106
      ],
      [
        102
      ],
      [
        108
      ]
    ],
    "SelectAffix": [],
    "ScoreRank": [],
    "LimitTime": 0,
    "ScoreAward": [],
    "KeyReward": []
  },
  "1223": {
    "DungeonId": 1223,
    "DungeonGroup": 5,
    "StarLevel": 3,
    "LabelPic": "ui/textures/herodungeon/hero_dungeon_tab_06",
    "Background": "ui/textures/dungeon_textures/dungeon_julong_3",
    "MasterModePic": "ui/textures/hero_dungeon_master/master_julong_title_01",
    "ModelId": 1,
    "EffectId": "1",
    "ExtraTarget": [],
    "BaseRatio": 100,
    "Affix": [],
    "SwitchAffix": [],
    "SelectAffix": [],
    "ScoreRank": [],
    "LimitTime": 0,
    "ScoreAward": [],
    "KeyReward": []
  },
  "1331": {
    "DungeonId": 1331,
    "DungeonGroup": 6,
    "StarLevel": 1,
    "LabelPic": "ui/textures/herodungeon/hero_dungeon_tab_underandera_01",
    "Background": "ui/textures/dungeon_textures/dungeon_underandera_1",
    "MasterModePic": "",
    "ModelId": 1,
    "EffectId": "1",
    "ExtraTarget": [],
    "BaseRatio": 100,
    "Affix": [],
    "SwitchAffix": [
      [
        115
      ],
      [
        104
      ],
      [
        106
      ],
      [
        102
      ],
      [
        108
      ],
      [
        104
      ],
      [
        106
      ],
      [
        102
      ],
      [
        108
      ],
      [
        104
      ],
      [
        106
      ],
      [
        102
      ],
      [
        108
      ]
    ],
    "SelectAffix": [],
    "ScoreRank": [],
    "LimitTime": 0,
    "ScoreAward": [],
    "KeyReward": []
  },
  "1332": {
    "DungeonId": 1332,
    "DungeonGroup": 6,
    "StarLevel": 2,
    "LabelPic": "ui/textures/herodungeon/hero_dungeon_tab_underandera_02",
    "Background": "ui/textures/dungeon_textures/dungeon_underandera_2",
    "MasterModePic": "",
    "ModelId": 1,
    "EffectId": "1",
    "ExtraTarget": [],
    "BaseRatio": 100,
    "Affix": [],
    "SwitchAffix": [
      [
        115
      ],
      [
        104
      ],
      [
        106
      ],
      [
        102
      ],
      [
        108
      ],
      [
        104
      ],
      [
        106
      ],
      [
        102
      ],
      [
        108
      ],
      [
        104
      ],
      [
        106
      ],
      [
        102
      ],
      [
        108
      ]
    ],
    "SelectAffix": [],
    "ScoreRank": [],
    "LimitTime": 0,
    "ScoreAward": [],
    "KeyReward": []
  },
  "1333": {
    "DungeonId": 1333,
    "DungeonGroup": 6,
    "StarLevel": 3,
    "LabelPic": "ui/textures/herodungeon/hero_dungeon_tab_underandera_03",
    "Background": "ui/textures/dungeon_textures/dungeon_underandera_3",
    "MasterModePic": "ui/textures/hero_dungeon_master/master_anying_title_01",
    "ModelId": 1,
    "EffectId": "1",
    "ExtraTarget": [],
    "BaseRatio": 100,
    "Affix": [],
    "SwitchAffix": [],
    "SelectAffix": [],
    "ScoreRank": [],
    "LimitTime": 0,
    "ScoreAward": [],
    "KeyReward": []
  }
}