{
  "1": {
    "Id": 1,
    "SceneLoadType": 0,
    "SceneFile": "scenes/scene_login"
  },
  "2": {
    "Id": 2,
    "SceneLoadType": 0,
    "SceneFile": "scenes/fightingtest"
  },
  "3": {
    "Id": 3,
    "SceneLoadType": 1,
    "SceneFile": "scenes/fld001"
  },
  "4": {
    "Id": 4,
    "SceneLoadType": 1,
    "SceneFile": "scenes/cty001"
  },
  "5": {
    "Id": 5,
    "SceneLoadType": 0,
    "SceneFile": "scenes/dng_main_1001_tina"
  },
  "6": {
    "Id": 6,
    "SceneLoadType": 0,
    "SceneFile": "scenes/dng_main_1101_tower"
  },
  "7": {
    "Id": 7,
    "SceneLoadType": 0,
    "SceneFile": "scenes/dng_hero_1121_tower"
  },
  "9": {
    "Id": 9,
    "SceneLoadType": 0,
    "SceneFile": "scenes/cty001_interior_002"
  },
  "10": {
    "Id": 10,
    "SceneLoadType": 1,
    "SceneFile": "scenes/testdng001"
  },
  "11": {
    "Id": 11,
    "SceneLoadType": 1,
    "SceneFile": "scenes/testdng002"
  },
  "12": {
    "Id": 12,
    "SceneLoadType": 1,
    "SceneFile": "scenes/test3c"
  },
  "14": {
    "Id": 14,
    "SceneLoadType": 0,
    "SceneFile": "scenes/dng_dmj_001"
  },
  "15": {
    "Id": 15,
    "SceneLoadType": 0,
    "SceneFile": "scenes/dng_dmj_002"
  },
  "16": {
    "Id": 16,
    "SceneLoadType": 0,
    "SceneFile": "scenes/dng_dmj_003"
  },
  "17": {
    "Id": 17,
    "SceneLoadType": 0,
    "SceneFile": "scenes/dng_dmj_002_mp"
  },
  "18": {
    "Id": 18,
    "SceneLoadType": 0,
    "SceneFile": "scenes/dng_dmj_004"
  },
  "19": {
    "Id": 19,
    "SceneLoadType": 0,
    "SceneFile": "scenes/dng_dmj_005"
  },
  "20": {
    "Id": 20,
    "SceneLoadType": 0,
    "SceneFile": "scenes/dng_dmj_006"
  },
  "21": {
    "Id": 21,
    "SceneLoadType": 1,
    "SceneFile": "scenes/cty001_interior_001"
  },
  "22": {
    "Id": 22,
    "SceneLoadType": 0,
    "SceneFile": "scenes/dng_dmj_007"
  },
  "23": {
    "Id": 23,
    "SceneLoadType": 0,
    "SceneFile": "scenes/dng_dmj_008"
  },
  "24": {
    "Id": 24,
    "SceneLoadType": 0,
    "SceneFile": "scenes/dng_dmj_001_mp"
  },
  "25": {
    "Id": 25,
    "SceneLoadType": 0,
    "SceneFile": "scenes/dng_dmj_005_mp"
  },
  "26": {
    "Id": 26,
    "SceneLoadType": 0,
    "SceneFile": "scenes/dng_main_1201_dragonscar"
  },
  "27": {
    "Id": 27,
    "SceneLoadType": 0,
    "SceneFile": "scenes/dng_branch_6011_carniman"
  },
  "28": {
    "Id": 28,
    "SceneLoadType": 0,
    "SceneFile": "scenes/dng_branch_6001_goblin"
  },
  "29": {
    "Id": 29,
    "SceneLoadType": 1,
    "SceneFile": "scenes/fld002"
  },
  "30": {
    "Id": 30,
    "SceneLoadType": 1,
    "SceneFile": "scenes/union_001"
  },
  "33": {
    "Id": 33,
    "SceneLoadType": 0,
    "SceneFile": "scenes/arn001"
  },
  "71": {
    "Id": 71,
    "SceneLoadType": 1,
    "SceneFile": "scenes/fld001_north"
  },
  "72": {
    "Id": 72,
    "SceneLoadType": 1,
    "SceneFile": "scenes/fld001_east"
  },
  "73": {
    "Id": 73,
    "SceneLoadType": 1,
    "SceneFile": "scenes/fld001_03_dragonscar"
  },
  "74": {
    "Id": 74,
    "SceneLoadType": 1,
    "SceneFile": "scenes/fld001_04_underground"
  },
  "75": {
    "Id": 75,
    "SceneLoadType": 1,
    "SceneFile": "scenes/fld001_05_underwater"
  },
  "30001": {
    "Id": 30001,
    "SceneLoadType": 0,
    "SceneFile": "scenes/home_system_outdoor_001"
  },
  "98": {
    "Id": 98,
    "SceneLoadType": 1,
    "SceneFile": "scenes/guild_lego_building"
  },
  "40001": {
    "Id": 40001,
    "SceneLoadType": 0,
    "SceneFile": "scenes/community_house_interior_001"
  },
  "40002": {
    "Id": 40002,
    "SceneLoadType": 2,
    "SceneFile": "scenes/house_story_visuallayer40001_small"
  },
  "40003": {
    "Id": 40003,
    "SceneLoadType": 2,
    "SceneFile": "scenes/house_story_visuallayer40001_medium"
  },
  "40004": {
    "Id": 40004,
    "SceneLoadType": 2,
    "SceneFile": "scenes/house_story_visuallayer40001"
  },
  "40": {
    "Id": 40,
    "SceneLoadType": 0,
    "SceneFile": "scenes/dng_main_5002_engramsea"
  },
  "7150": {
    "Id": 7150,
    "SceneLoadType": 1,
    "SceneFile": "scenes/dng_worldboss_001"
  },
  "7151": {
    "Id": 7151,
    "SceneLoadType": 0,
    "SceneFile": "scenes/dng_worldboss_002"
  },
  "31": {
    "Id": 31,
    "SceneLoadType": 0,
    "SceneFile": "scenes/dng_main_1301_underandera"
  },
  "50": {
    "Id": 50,
    "SceneLoadType": 0,
    "SceneFile": "scenes/dng_twr_001"
  },
  "51": {
    "Id": 51,
    "SceneLoadType": 0,
    "SceneFile": "scenes/dng_twr_002"
  },
  "5220": {
    "Id": 5220,
    "SceneLoadType": 0,
    "SceneFile": "scenes/cty001_interior_003"
  },
  "5401": {
    "Id": 5401,
    "SceneLoadType": 0,
    "SceneFile": "scenes/fld001_interior_001"
  },
  "5604": {
    "Id": 5604,
    "SceneLoadType": 2,
    "SceneFile": "scenes/fld002_sublevel_001"
  },
  "7070": {
    "Id": 7070,
    "SceneLoadType": 2,
    "SceneFile": "scenes/fld001_story_worldevent7070"
  },
  "7071": {
    "Id": 7071,
    "SceneLoadType": 2,
    "SceneFile": "scenes/fld001_story_worldevent7071"
  },
  "7072": {
    "Id": 7072,
    "SceneLoadType": 2,
    "SceneFile": "scenes/fld001_story_worldevent7072"
  },
  "7073": {
    "Id": 7073,
    "SceneLoadType": 2,
    "SceneFile": "scenes/fld001_story_worldevent7073"
  },
  "7075": {
    "Id": 7075,
    "SceneLoadType": 2,
    "SceneFile": "scenes/fld001_story_worldevent7075"
  },
  "7085": {
    "Id": 7085,
    "SceneLoadType": 2,
    "SceneFile": "scenes/fld001_story_worldevent7085"
  },
  "10001": {
    "Id": 10001,
    "SceneLoadType": 2,
    "SceneFile": "scenes/fld001_story_visuallayer5204"
  },
  "10002": {
    "Id": 10002,
    "SceneLoadType": 2,
    "SceneFile": "scenes/dng_main_1101_tower_story_freeze"
  },
  "5500": {
    "Id": 5500,
    "SceneLoadType": 2,
    "SceneFile": "scenes/cty001_story_warcity"
  },
  "5501": {
    "Id": 5501,
    "SceneLoadType": 2,
    "SceneFile": "scenes/cty001_story_warcitycitizen"
  },
  "5212": {
    "Id": 5212,
    "SceneLoadType": 2,
    "SceneFile": "scenes/fld001_story_visuallayer5212"
  },
  "5110": {
    "Id": 5110,
    "SceneLoadType": 2,
    "SceneFile": "scenes/cty001_story_fireworks"
  },
  "5111": {
    "Id": 5111,
    "SceneLoadType": 2,
    "SceneFile": "scenes/cty001_story_fireworks_festival"
  },
  "5019": {
    "Id": 5019,
    "SceneLoadType": 2,
    "SceneFile": "scenes/cty001_story_visuallayer5019"
  },
  "5041": {
    "Id": 5041,
    "SceneLoadType": 2,
    "SceneFile": "scenes/cty001_story_ship"
  },
  "10020": {
    "Id": 10020,
    "SceneLoadType": 0,
    "SceneFile": "scenes/cs_fashion_suit01"
  },
  "10021": {
    "Id": 10021,
    "SceneLoadType": 0,
    "SceneFile": "scenes/cs_fashion_suit02"
  },
  "1401": {
    "Id": 1401,
    "SceneLoadType": 0,
    "SceneFile": "scenes/dng_raid_001"
  },
  "1402": {
    "Id": 1402,
    "SceneLoadType": 0,
    "SceneFile": "scenes/dng_raid_001"
  },
  "1403": {
    "Id": 1403,
    "SceneLoadType": 0,
    "SceneFile": "scenes/dng_raid_001_01"
  },
  "1404": {
    "Id": 1404,
    "SceneLoadType": 0,
    "SceneFile": "scenes/dng_raid_001_02"
  },
  "1405": {
    "Id": 1405,
    "SceneLoadType": 0,
    "SceneFile": "scenes/dng_raid_001_03"
  },
  "1406": {
    "Id": 1406,
    "SceneLoadType": 0,
    "SceneFile": "scenes/dng_raid_001_04"
  },
  "1407": {
    "Id": 1407,
    "SceneLoadType": 0,
    "SceneFile": "scenes/dng_raid_001_05"
  },
  "1500": {
    "Id": 1500,
    "SceneLoadType": 0,
    "SceneFile": "scenes/union_activity_001"
  },
  "5602": {
    "Id": 5602,
    "SceneLoadType": 0,
    "SceneFile": "scenes/fld002_interior_001"
  },
  "1501": {
    "Id": 1501,
    "SceneLoadType": 2,
    "SceneFile": "scenes/union_activity_sublevel_001"
  },
  "1502": {
    "Id": 1502,
    "SceneLoadType": 2,
    "SceneFile": "scenes/union_activity_sublevel_002"
  },
  "171001": {
    "Id": 171001,
    "SceneLoadType": 0,
    "SceneFile": "scenes/home_system_guidetask"
  },
  "13001": {
    "Id": 13001,
    "SceneLoadType": 0,
    "SceneFile": "scenes/dng_raid_001"
  },
  "70001": {
    "Id": 70001,
    "SceneLoadType": 2,
    "SceneFile": "scenes/fld001_story_raidentrance"
  }
}